LICENSE
newsletter/__init__.py
newsletter/admin.py
newsletter/apps.py
newsletter/cms_apps.py
newsletter/cms_plugins.py
newsletter/context_processors.py
newsletter/forms.py
newsletter/migrations/0001_initial.py
newsletter/migrations/0002_auto_20200623_1442.py
newsletter/migrations/0003_auto_20200916_0730.py
newsletter/migrations/0004_add_climatecare_fields.py
newsletter/migrations/__init__.py
newsletter/models.py
newsletter/templates/base.html
newsletter/templates/newsletter/index.html
newsletter/templates/newsletter/plugin.html
newsletter/tests/__init__.py
newsletter/tests/conftest.py
newsletter/tests/test_cms_apps.py
newsletter/tests/test_models.py
newsletter/tests/test_views.py
newsletter/tests/urls.py
newsletter/urls.py
newsletter/views.py
giant_newsletter-0.3.5.dist-info/LICENSE
giant_newsletter-0.3.5.dist-info/METADATA
giant_newsletter-0.3.5.dist-info/WHEEL
giant_newsletter-0.3.5.dist-info/RECORD
