Metadata-Version: 2.1
Name: giant-newsletter
Version: 0.3.5
Summary: A small reusable package that adds a Newsletter app to a project
Home-page: https://github.com/giantmade/giant-newsletter
License: MIT
Keywords: newsletter,app
Author: Will-Hoey
Author-email: will.hoey@giantmade.com
Requires-Python: >=3.9,<4.0
Classifier: Environment :: Console
Classifier: License :: OSI Approved :: MIT License
Classifier: Operating System :: OS Independent
Classifier: Programming Language :: Python :: 3
Classifier: Programming Language :: Python :: 3.9
Classifier: Programming Language :: Python :: 3.10
Classifier: Programming Language :: Python :: 3.11
Classifier: Topic :: Software Development :: Documentation
Classifier: Topic :: Software Development :: Libraries :: Python Modules
Requires-Dist: giant-mixins
Project-URL: Repository, https://github.com/giantmade/giant-newsletter
